copa/__init__.py
copa/cli.py
copa/copa.py
copa-0.1.1.dist-info/licenses/LICENSE
copa-0.1.1.dist-info/METADATA
copa-0.1.1.dist-info/WHEEL
copa-0.1.1.dist-info/entry_points.txt
copa-0.1.1.dist-info/top_level.txt
copa-0.1.1.dist-info/RECORD
