Metadata-Version: 2.4
Name: copa
Version: 0.1.1
Summary: Configure, Orchestrate and Provision Applications
Author-email: Ian Edwards <ian@myacorn.com>
License: MIT
Classifier: Programming Language :: Python :: 3
Classifier: License :: OSI Approved :: MIT License
Classifier: Operating System :: OS Independent
Requires-Python: >=3.8
License-File: LICENSE
Requires-Dist: typer~=0.9.0
Dynamic: license-file
